et_stopwatch/__init__.py
et_stopwatch-1.3.1.dist-info/LICENSE
et_stopwatch-1.3.1.dist-info/WHEEL
et_stopwatch-1.3.1.dist-info/entry_points.txt
et_stopwatch-1.3.1.dist-info/METADATA
et_stopwatch-1.3.1.dist-info/RECORD
