Metadata-Version: 2.1
Name: et-stopwatch
Version: 1.3.1
Summary: A class for timing code (start/stop, context manager, decorator).
Home-page: https://github.com/etijskens/et-stopwatch
License: MIT
Keywords: packaging,poetry
Author: Engelbert Tijskens
Author-email: engelbert.tijskens@uantwerpen.be
Requires-Python: >=3.7,<4.0
Classifier: License :: OSI Approved :: MIT License
Classifier: Programming Language :: Python :: 3
Classifier: Programming Language :: Python :: 3.7
Classifier: Programming Language :: Python :: 3.8
Classifier: Programming Language :: Python :: 3.9
Classifier: Programming Language :: Python :: 3.10
Classifier: Programming Language :: Python :: 3.11
Project-URL: Repository, https://github.com/etijskens/et-stopwatch
